{
  "General": {
    "Success": "Success",
    "Error": "Error"
  },
  "Jwt": {
    "TokenNotFound": "Token Not Found",
    "ExpiredToken": "Expired Token",
    "InvalidToken": "Invalid Token"
  },
  "HttpStatus": {
    "Success": "Success",
    "NotAllowed": "Not Allowed",
    "BadRequest": "Bad Request",
    "NotFound": "Not Found",
    "InternalServerError": "Something went wrong",
    "Unauthorized": "Unauthorized"
  },
  "User": {
    "NotFound": "User Not Found",
    "UserExist": "Credentials are taken",
    "EnterAddress": "Please enter address",
    "RoleNotFound": "Users role not found",
    "Unauthorized": "Unauthorized User"
  },
  "Api": {
    "NotFound": "Api Not Found",
    "RoutePathNotFound": "Api Route Path Not Found"
  },
  "Role": {
    "NotFound": "Rol Not Found"
  },
  "ApiRole": {
    "NotFound": "Api Role Not Found"
  },
  "UserRole": {
    "NotFound": "User Role NotFound"
  },
  "Product": {
    "NotFound": "Product Not Found",
    "EnterProductId": "Please Enter Product Id"
  },
  "Merchant": {
    "NotFound": "Merchant Not Found"
  },
  "Cart": {
    "ProductHasRemoved": "Product has already removed from cart",
    "UserCartNotFound": "Customers cart not found. User no: {0}"
  },
  "Category": {
    "EnterCategoryName": "Please Enter a Category Name",
    "NotFound": "Category Not Found",
    "AlreadyAdded": "{0} is Already Added",
    "ParentCategoryNotFound": "Parent Category Not Found"
  },
  "Carousel": {
    "NotFound": "Carousel Not Found"
  },
  "Login": {
    "CheckCredentials": "User not found. Please check your credentials"
  },
  "ProductDetail": {
    "ChooseProductToAdd": "Please choose product to add detail",
    "ChooseMerchantToAdd": "Please choose merchant to add detail",
    "CheckCount": "Product count must be greater than 0",
    "ChooseProductToGetDetails": "Please choose product to get detail"
  },
  "LoginRequestValidator": {
    "NotNull": "Please enter email, username or mobileno",
    "PasswordNotNull": "Please enter your password"
  },
  "CreateAddressRequestValidator": {
    "CountryNotNull": "Country must be filled",
    "ProvinceNotNull": "Province must be filled",
    "DistrictNotNull": "District must be filled",
    "AddressInfoNotNull": "AddressInfo must be filled",
    "AddressTypeNotNull": "AddressType must be filled",
    "MobileNo": "Please enter a proper Mobile No"
  },
  "CreateUserRequestValidator": {
    "NameNotNull": "Name must be filled",
    "NameMinLength": "Minimum Name length can be two",
    "NameMaxLength": "Maximum Name length can be fifty",
    "SurNameNotNull": "SurName can not be null",
    "SurNameMinLength": "Minimum Surname length can be two",
    "SurNameMaxLength": "Maximum Surname length can be fifty",
    "UserNameNotNull": "UserName must be filled",
    "EmailNotNull": "Email must be filled",
    "PasswordNotNull": "Password must be filled",
    "PasswordLength": "Password length can be between 6-50",
    "MobileNoNotNull": "Mobile No must be filled",
    "MobileNo": "Please enter a valid mobile no",
    "BirthDate": "Birth date must be greater then 19000101"
  },
  "Logging": {
    "ServiceStarted": "Service is started: {0}",
    "ServiceFinished": "Service is finished: {0}",
    "HttpServiceFinished": "{0} ms elapsed."
  },
  "Localization": {
    "KeyCanNotBeNull": "Key can not be null.",
    "KeyNotFound": "Key not found: {0}",
    "KeyIsNull": "Key which will be translated is null."
  }
}